hyperpocket_gemini/__init__.py
hyperpocket_gemini/pocket_gemini.py
hyperpocket_gemini/util/__init__.py
hyperpocket_gemini/util/tool_to_gemini_spec.py
hyperpocket_gemini-0.5.7.dist-info/METADATA
hyperpocket_gemini-0.5.7.dist-info/WHEEL
hyperpocket_gemini-0.5.7.dist-info/RECORD
