Metadata-Version: 2.4
Name: hyperpocket-gemini
Version: 0.5.7
Requires-Python: >=3.11
Requires-Dist: google-genai>=1.0.0
Requires-Dist: hyperpocket>=0.0.3
